colabtunnel/__init__.py
colabtunnel/colabtunnel.py
colabtunnel-0.0.7.dist-info/LICENSE
colabtunnel-0.0.7.dist-info/METADATA
colabtunnel-0.0.7.dist-info/WHEEL
colabtunnel-0.0.7.dist-info/top_level.txt
colabtunnel-0.0.7.dist-info/RECORD
