Metadata-Version: 2.1
Name: colabtunnel
Version: 0.0.7
Summary: Connect to Google Colab VM locally from VSCode
Home-page: https://github.com/amitness/colab-tunnel
Author: Amit Chaudhary
Author-email: meamitkc@gmail.com
License: MIT
Classifier: Development Status :: 3 - Alpha
Classifier: Intended Audience :: Developers
Classifier: Topic :: Software Development :: Build Tools
Classifier: License :: OSI Approved :: MIT License
Classifier: Programming Language :: Python :: 3
Requires-Python: >=3.7
License-File: LICENSE
